atmosphericRadiationDoseAndFlux/__init__.py
atmosphericRadiationDoseAndFlux/doseAndFluxCalculator.py
atmosphericRadiationDoseAndFlux/particle.py
atmosphericRadiationDoseAndFlux/particleResponse.py
atmosphericRadiationDoseAndFlux/responseFileParameters.py
atmosphericRadiationDoseAndFlux/settings.py
atmosphericRadiationDoseAndFlux/units.py
atmosphericRadiationDoseAndFlux/data/__init__.py
atmosphericRadiationDoseAndFlux/data/alpha/__init__.py
atmosphericRadiationDoseAndFlux/data/alpha/adose.rpf
atmosphericRadiationDoseAndFlux/data/alpha/dosee.rpf
atmosphericRadiationDoseAndFlux/data/alpha/edose.rpf
atmosphericRadiationDoseAndFlux/data/alpha/neutron.rpf
atmosphericRadiationDoseAndFlux/data/proton/__init__.py
atmosphericRadiationDoseAndFlux/data/proton/adose.rpf
atmosphericRadiationDoseAndFlux/data/proton/dosee.rpf
atmosphericRadiationDoseAndFlux/data/proton/edose.rpf
atmosphericRadiationDoseAndFlux/data/proton/neutron.rpf
tests/__init__.py
tests/test_general.py
atmosphericRadiationDoseAndFlux-1.0.12.dist-info/LICENSE
atmosphericRadiationDoseAndFlux-1.0.12.dist-info/METADATA
atmosphericRadiationDoseAndFlux-1.0.12.dist-info/WHEEL
atmosphericRadiationDoseAndFlux-1.0.12.dist-info/top_level.txt
atmosphericRadiationDoseAndFlux-1.0.12.dist-info/RECORD
