Metadata-Version: 2.2
Name: atmosphericRadiationDoseAndFlux
Version: 1.0.12
Summary: Python library for calculating doses and fluxes at a particular altitude given an input spectrum
Home-page: https://github.com/ssc-maire/DoseAndFluxCalculator
Author: Space Environment and Protection Group, University of Surrey
License: CC BY-NC-SA 4.0
Keywords: atmosphere radiation space weather cosmic rays spectrum alpha particles yield response dose rates ambient effective GLE sun solar aviation neutron monitor
License-File: LICENSE
Requires-Dist: importlib_resources>=5.10.0
Requires-Dist: numpy>=1.21.6
Requires-Dist: pandas>=1.3.5
Requires-Dist: ParticleRigidityCalculationTools>=1.5.4
Requires-Dist: setuptools>=45.2.0
Dynamic: author
Dynamic: description
Dynamic: description-content-type
Dynamic: home-page
Dynamic: keywords
Dynamic: license
Dynamic: requires-dist
Dynamic: summary
